{
   "notices" : [
      {
         "description" : [
            "Please note that this RDAP service is NOT provided by the IANA.",
            "",
            "For more information, please see https://about.rdap.org"
         ],
         "title" : "About This Service"
      },
      {
         "title" : "Comments",
         "description" : [
            "IANA WHOIS server",
            "for more information on IANA, visit http://www.iana.org",
            "This query returned 1 object"
         ]
      }
   ],
   "remarks" : [
      {
         "description" : [
            "The port-43 whois service for this TLD is ."
         ],
         "title" : "Whois Service"
      },
      {
         "title" : "Remark",
         "description" : [
            "Registration information: "
         ]
      },
      {
         "description" : [
            "IANA"
         ],
         "title" : "Source"
      }
   ],
   "handle" : "mv",
   "nameservers" : [
      {
         "ipAddresses" : {
            "v4" : [
               "204.61.216.24"
            ],
            "v6" : []
         },
         "objectClassName" : "nameserver",
         "ldhName" : "MV-NS.ANYCAST.PCH.NET"
      },
      {
         "ipAddresses" : {
            "v4" : [
               "202.1.192.196"
            ],
            "v6" : []
         },
         "objectClassName" : "nameserver",
         "ldhName" : "NS.DHIVEHINET.NET.MV"
      },
      {
         "ldhName" : "NS2.DHIVEHINET.NET.MV",
         "objectClassName" : "nameserver",
         "ipAddresses" : {
            "v4" : [
               "202.1.201.201"
            ],
            "v6" : []
         }
      }
   ],
   "ldhName" : "mv",
   "status" : [
      "active"
   ],
   "events" : [
      {
         "eventAction" : "registration",
         "eventDate" : "1996-09-25"
      },
      {
         "eventDate" : "2021-01-13",
         "eventAction" : "last changed"
      },
      {
         "eventAction" : "last update of RDAP database",
         "eventDate" : "2023-07-26T12:03:34"
      }
   ],
   "objectClassName" : "domain",
   "links" : [
      {
         "rel" : "related",
         "href" : "https://www.iana.org/domains/root/db/mv.html",
         "title" : "Entry for this TLD in the Root Zone Database"
      },
      {
         "rel" : "related",
         "title" : "About RDAP",
         "href" : "https://about.rdap.org"
      }
   ],
   "rdapConformance" : [
      "rdap_level_0"
   ],
   "port43" : "whois.iana.org",
   "entities" : [
      {
         "handle" : "mv-technical",
         "roles" : [
            "technical"
         ],
         "objectClassName" : "entity",
         "vcardArray" : [
            "vcard",
            [
               [
                  "version",
                  {},
                  "text",
                  "4.0"
               ],
               [
                  "fn",
                  {},
                  "text",
                  "Network Administrator - NOC"
               ],
               [
                  "org",
                  {},
                  "text",
                  "Dhiraagu Pvt. Ltd. (DHIVEHINET)"
               ],
               [
                  "adr",
                  {
                     "label" : "19 Medhuziyaaraiy Magu\nMale 20-02\nMaldives"
                  },
                  "text",
                  [
                     "",
                     "",
                     "",
                     "",
                     "",
                     "",
                     ""
                  ]
               ],
               [
                  "tel",
                  {},
                  "text",
                  "+960 311222"
               ],
               [
                  "tel",
                  {
                     "type" : "fax"
                  },
                  "text",
                  "+960 3343088"
               ],
               [
                  "email",
                  {},
                  "text",
                  "noc@dhiraagu.com.mv"
               ]
            ]
         ]
      },
      {
         "handle" : "mv-administrative",
         "roles" : [
            "administrative"
         ],
         "objectClassName" : "entity",
         "vcardArray" : [
            "vcard",
            [
               [
                  "version",
                  {},
                  "text",
                  "4.0"
               ],
               [
                  "fn",
                  {},
                  "text",
                  "NOC Engineer"
               ],
               [
                  "org",
                  {},
                  "text",
                  "Dhiraagu Pvt. Ltd. (DHIVEHINET)"
               ],
               [
                  "adr",
                  {
                     "label" : "19 Medhuziyaaraiy Magu\nMale 20-02\nMaldives"
                  },
                  "text",
                  [
                     "",
                     "",
                     "",
                     "",
                     "",
                     "",
                     ""
                  ]
               ],
               [
                  "tel",
                  {},
                  "text",
                  "+960 771803"
               ],
               [
                  "tel",
                  {
                     "type" : "fax"
                  },
                  "text",
                  "+960 3343088"
               ],
               [
                  "email",
                  {},
                  "text",
                  "noc@dhiraagu.com.mv"
               ]
            ]
         ]
      },
      {
         "roles" : [
            "registrant"
         ],
         "handle" : "mv-registrant",
         "vcardArray" : [
            "vcard",
            [
               [
                  "version",
                  {},
                  "text",
                  "4.0"
               ],
               [
                  "org",
                  {},
                  "text",
                  "Dhiraagu Pvt. Ltd. (DHIVEHINET)"
               ],
               [
                  "adr",
                  {
                     "label" : "19 Medhuziyaaraiy Magu\nMale 20-02\nMaldives"
                  },
                  "text",
                  [
                     "",
                     "",
                     "",
                     "",
                     "",
                     "",
                     ""
                  ]
               ]
            ]
         ],
         "objectClassName" : "entity"
      }
   ]
}
