{
   "secureDNS" : {
      "dsData" : [
         {
            "digest" : "90045c6e0579687c19d9318132095adbc9532831f3d175004d8e4a05fb05d268",
            "algorithm" : "8",
            "keyTag" : "8731",
            "digestType" : "2"
         }
      ],
      "delegationSigned" : true
   },
   "rdapConformance" : [
      "rdap_level_0"
   ],
   "entities" : [
      {
         "objectClassName" : "entity",
         "vcardArray" : [
            "vcard",
            [
               [
                  "version",
                  {},
                  "text",
                  "4.0"
               ],
               [
                  "org",
                  {},
                  "text",
                  "EURid vzw"
               ],
               [
                  "adr",
                  {
                     "label" : "Telecomlaan 9\nDiegem 1831\nBelgium"
                  },
                  "text",
                  [
                     "",
                     "",
                     "",
                     "",
                     "",
                     "",
                     ""
                  ]
               ]
            ]
         ],
         "roles" : [
            "registrant"
         ],
         "handle" : "xn--e1a4c-registrant"
      },
      {
         "handle" : "xn--e1a4c-administrative",
         "roles" : [
            "administrative"
         ],
         "objectClassName" : "entity",
         "vcardArray" : [
            "vcard",
            [
               [
                  "version",
                  {},
                  "text",
                  "4.0"
               ],
               [
                  "fn",
                  {},
                  "text",
                  "Peter Janssen"
               ],
               [
                  "org",
                  {},
                  "text",
                  "EURid vzw/asbl"
               ],
               [
                  "adr",
                  {
                     "label" : "Telecomlaan 9\nDiegem 1831\nBelgium"
                  },
                  "text",
                  [
                     "",
                     "",
                     "",
                     "",
                     "",
                     "",
                     ""
                  ]
               ],
               [
                  "tel",
                  {},
                  "text",
                  "+32 2 401 27 50"
               ],
               [
                  "tel",
                  {
                     "type" : "fax"
                  },
                  "text",
                  "+32 2 401 27 51"
               ],
               [
                  "email",
                  {},
                  "text",
                  "domain-admin@eurid.eu"
               ]
            ]
         ]
      },
      {
         "roles" : [
            "technical"
         ],
         "handle" : "xn--e1a4c-technical",
         "objectClassName" : "entity",
         "vcardArray" : [
            "vcard",
            [
               [
                  "version",
                  {},
                  "text",
                  "4.0"
               ],
               [
                  "fn",
                  {},
                  "text",
                  "Technical Department"
               ],
               [
                  "org",
                  {},
                  "text",
                  "EURid vzw"
               ],
               [
                  "adr",
                  {
                     "label" : "Telecomlaan 9\nDiegem 1831\nBelgium"
                  },
                  "text",
                  [
                     "",
                     "",
                     "",
                     "",
                     "",
                     "",
                     ""
                  ]
               ],
               [
                  "tel",
                  {},
                  "text",
                  "+32 2 401 27 50"
               ],
               [
                  "tel",
                  {
                     "type" : "fax"
                  },
                  "text",
                  "+32 2 401 27 51"
               ],
               [
                  "email",
                  {},
                  "text",
                  "domain-tech@eurid.eu"
               ]
            ]
         ]
      }
   ],
   "port43" : "whois.iana.org",
   "links" : [
      {
         "href" : "https://www.iana.org/domains/root/db/xn--e1a4c.html",
         "title" : "Entry for this TLD in the Root Zone Database",
         "rel" : "related"
      },
      {
         "href" : "https://about.rdap.org",
         "title" : "About RDAP",
         "rel" : "related"
      },
      {
         "rel" : "related",
         "href" : "http://www.registry.eu",
         "title" : "URL for registration services"
      }
   ],
   "objectClassName" : "domain",
   "nameservers" : [
      {
         "ldhName" : "BE.DNS.EU",
         "objectClassName" : "nameserver",
         "ipAddresses" : {
            "v6" : [
               "2001:978:2:1:0:0:93:2"
            ],
            "v4" : [
               "149.38.1.26"
            ]
         }
      },
      {
         "ipAddresses" : {
            "v4" : [
               "193.2.221.62"
            ],
            "v6" : [
               "2001:1470:8000:100:0:0:0:62"
            ]
         },
         "objectClassName" : "nameserver",
         "ldhName" : "SI.DNS.EU"
      },
      {
         "ldhName" : "W.DNS.EU",
         "objectClassName" : "nameserver",
         "ipAddresses" : {
            "v4" : [
               "194.0.25.28"
            ],
            "v6" : [
               "2001:678:20:0:0:0:0:28"
            ]
         }
      },
      {
         "objectClassName" : "nameserver",
         "ldhName" : "X.DNS.EU",
         "ipAddresses" : {
            "v4" : [
               "185.151.141.1"
            ],
            "v6" : [
               "2a02:568:fe00:0:0:0:0:6575"
            ]
         }
      },
      {
         "ipAddresses" : {
            "v6" : [
               "2001:67c:1010:23:0:0:0:53"
            ],
            "v4" : [
               "194.146.106.90"
            ]
         },
         "objectClassName" : "nameserver",
         "ldhName" : "Y.DNS.EU"
      }
   ],
   "ldhName" : "xn--e1a4c",
   "events" : [
      {
         "eventDate" : "2015-12-08",
         "eventAction" : "registration"
      },
      {
         "eventAction" : "last changed",
         "eventDate" : "2023-03-07"
      },
      {
         "eventDate" : "2023-07-26T12:04:05",
         "eventAction" : "last update of RDAP database"
      }
   ],
   "status" : [
      "active"
   ],
   "remarks" : [
      {
         "title" : "Whois Service",
         "description" : [
            "The port-43 whois service for this TLD is WHOIS.EU."
         ]
      },
      {
         "description" : [
            "Registration information: http://www.registry.eu"
         ],
         "title" : "Remark"
      },
      {
         "title" : "Source",
         "description" : [
            "IANA"
         ]
      }
   ],
   "notices" : [
      {
         "title" : "About This Service",
         "description" : [
            "Please note that this RDAP service is NOT provided by the IANA.",
            "",
            "For more information, please see https://about.rdap.org"
         ]
      },
      {
         "description" : [
            "IANA WHOIS server",
            "for more information on IANA, visit http://www.iana.org",
            "This query returned 1 object"
         ],
         "title" : "Comments"
      }
   ],
   "handle" : "xn--e1a4c"
}
