{
   "handle" : "career",
   "objectClassName" : "domain",
   "secureDNS" : {
      "delegationSigned" : true,
      "dsData" : [
         {
            "digestType" : "2",
            "keyTag" : "11480",
            "algorithm" : "8",
            "digest" : "252513a3ade85062b3943c4d19b9de1a0ae15176ac5d0c6d15c6b79b70f36ff8"
         }
      ]
   },
   "ldhName" : "career",
   "entities" : [
      {
         "vcardArray" : [
            "vcard",
            [
               [
                  "version",
                  {},
                  "text",
                  "4.0"
               ],
               [
                  "org",
                  {},
                  "text",
                  "dotCareer LLC"
               ],
               [
                  "adr",
                  {
                     "label" : "3029 Prospect Ave.\nCleveland OH 44115\nUnited States of America (the)"
                  },
                  "text",
                  [
                     "",
                     "",
                     "",
                     "",
                     "",
                     "",
                     ""
                  ]
               ]
            ]
         ],
         "roles" : [
            "registrant"
         ],
         "objectClassName" : "entity",
         "handle" : "career-registrant"
      },
      {
         "objectClassName" : "entity",
         "handle" : "career-technical",
         "roles" : [
            "technical"
         ],
         "vcardArray" : [
            "vcard",
            [
               [
                  "version",
                  {},
                  "text",
                  "4.0"
               ],
               [
                  "fn",
                  {},
                  "text",
                  "TLD Registry Services Technical"
               ],
               [
                  "org",
                  {},
                  "text",
                  "Nominet"
               ],
               [
                  "adr",
                  {
                     "label" : "Minerva House\nEdmund Halley Road\nOxford Science Park\nOxford OX4 4DQ\nUnited Kingdom of Great Britain and Northern Ireland (the)"
                  },
                  "text",
                  [
                     "",
                     "",
                     "",
                     "",
                     "",
                     "",
                     ""
                  ]
               ],
               [
                  "tel",
                  {},
                  "text",
                  "+44.1865332211"
               ],
               [
                  "email",
                  {},
                  "text",
                  "registrytechnical@nominet.uk"
               ]
            ]
         ]
      },
      {
         "objectClassName" : "entity",
         "handle" : "career-administrative",
         "vcardArray" : [
            "vcard",
            [
               [
                  "version",
                  {},
                  "text",
                  "4.0"
               ],
               [
                  "fn",
                  {},
                  "text",
                  "Ray Fassett"
               ],
               [
                  "org",
                  {},
                  "text",
                  "dotCareer LLC"
               ],
               [
                  "adr",
                  {
                     "label" : "3029 Prospect Ave.\nCleveland OH 44115\nUnited States of America (the)"
                  },
                  "text",
                  [
                     "",
                     "",
                     "",
                     "",
                     "",
                     "",
                     ""
                  ]
               ],
               [
                  "tel",
                  {},
                  "text",
                  "216-426-1500"
               ],
               [
                  "tel",
                  {
                     "type" : "fax"
                  },
                  "text",
                  "216-588-1558"
               ],
               [
                  "email",
                  {},
                  "text",
                  "ray@goto.jobs"
               ]
            ]
         ],
         "roles" : [
            "administrative"
         ]
      }
   ],
   "port43" : "whois.iana.org",
   "events" : [
      {
         "eventDate" : "2014-03-20",
         "eventAction" : "registration"
      },
      {
         "eventAction" : "last changed",
         "eventDate" : "2021-11-09"
      },
      {
         "eventAction" : "last update of RDAP database",
         "eventDate" : "2023-07-26T13:16:47"
      }
   ],
   "rdapConformance" : [
      "rdap_level_0"
   ],
   "status" : [
      "active"
   ],
   "remarks" : [
      {
         "description" : [
            "The port-43 whois service for this TLD is WHOIS.NIC.CAREER."
         ],
         "title" : "Whois Service"
      },
      {
         "title" : "Remark",
         "description" : [
            "Registration information: "
         ]
      },
      {
         "title" : "Source",
         "description" : [
            "IANA"
         ]
      }
   ],
   "notices" : [
      {
         "title" : "About This Service",
         "description" : [
            "Please note that this RDAP service is NOT provided by the IANA.",
            "",
            "For more information, please see https://about.rdap.org"
         ]
      },
      {
         "title" : "Comments",
         "description" : [
            "IANA WHOIS server",
            "for more information on IANA, visit http://www.iana.org",
            "This query returned 1 object"
         ]
      }
   ],
   "nameservers" : [
      {
         "ipAddresses" : {
            "v6" : [
               "2a01:618:403:0:0:0:0:121"
            ],
            "v4" : [
               "213.248.219.121"
            ]
         },
         "objectClassName" : "nameserver",
         "ldhName" : "DNS1.NIC.CAREER"
      },
      {
         "objectClassName" : "nameserver",
         "ipAddresses" : {
            "v6" : [
               "2401:fd80:403:0:0:0:0:121"
            ],
            "v4" : [
               "103.49.83.121"
            ]
         },
         "ldhName" : "DNS2.NIC.CAREER"
      },
      {
         "ldhName" : "DNS3.NIC.CAREER",
         "ipAddresses" : {
            "v4" : [
               "213.248.223.121"
            ],
            "v6" : [
               "2a01:618:407:0:0:0:0:121"
            ]
         },
         "objectClassName" : "nameserver"
      },
      {
         "ldhName" : "DNS4.NIC.CAREER",
         "ipAddresses" : {
            "v6" : [
               "2401:fd80:407:0:0:0:0:121"
            ],
            "v4" : [
               "43.230.51.121"
            ]
         },
         "objectClassName" : "nameserver"
      },
      {
         "ldhName" : "DNSA.NIC.CAREER",
         "ipAddresses" : {
            "v4" : [
               "156.154.100.3"
            ],
            "v6" : [
               "2001:502:ad09:0:0:0:0:3"
            ]
         },
         "objectClassName" : "nameserver"
      },
      {
         "ldhName" : "DNSB.NIC.CAREER",
         "ipAddresses" : {
            "v4" : [
               "156.154.101.3"
            ],
            "v6" : [
               "2001:502:2eda:0:0:0:0:3"
            ]
         },
         "objectClassName" : "nameserver"
      },
      {
         "objectClassName" : "nameserver",
         "ipAddresses" : {
            "v4" : [
               "156.154.102.3"
            ],
            "v6" : [
               "2610:a1:1009:0:0:0:0:3"
            ]
         },
         "ldhName" : "DNSC.NIC.CAREER"
      },
      {
         "ldhName" : "DNSD.NIC.CAREER",
         "objectClassName" : "nameserver",
         "ipAddresses" : {
            "v6" : [
               "2610:a1:1010:0:0:0:0:3"
            ],
            "v4" : [
               "156.154.103.3"
            ]
         }
      }
   ],
   "links" : [
      {
         "rel" : "related",
         "href" : "https://www.iana.org/domains/root/db/career.html",
         "title" : "Entry for this TLD in the Root Zone Database"
      },
      {
         "href" : "https://about.rdap.org",
         "rel" : "related",
         "title" : "About RDAP"
      }
   ]
}
