{
   "rdapConformance" : [
      "rdap_level_0"
   ],
   "status" : [
      "active"
   ],
   "remarks" : [
      {
         "title" : "Whois Service",
         "description" : [
            "The port-43 whois service for this TLD is WHOIS.DENIC.DE."
         ]
      },
      {
         "title" : "Remark",
         "description" : [
            "Registration information: http://www.denic.de/"
         ]
      },
      {
         "description" : [
            "IANA"
         ],
         "title" : "Source"
      }
   ],
   "notices" : [
      {
         "description" : [
            "Please note that this RDAP service is NOT provided by the IANA.",
            "",
            "For more information, please see https://about.rdap.org"
         ],
         "title" : "About This Service"
      },
      {
         "description" : [
            "IANA WHOIS server",
            "for more information on IANA, visit http://www.iana.org",
            "This query returned 1 object"
         ],
         "title" : "Comments"
      }
   ],
   "nameservers" : [
      {
         "ipAddresses" : {
            "v6" : [
               "2001:678:2:0:0:0:0:53"
            ],
            "v4" : [
               "194.0.0.53"
            ]
         },
         "objectClassName" : "nameserver",
         "ldhName" : "A.NIC.DE"
      },
      {
         "ldhName" : "F.NIC.DE",
         "objectClassName" : "nameserver",
         "ipAddresses" : {
            "v4" : [
               "81.91.164.5"
            ],
            "v6" : [
               "2a02:568:0:2:0:0:0:53"
            ]
         }
      },
      {
         "ldhName" : "L.DE.NET",
         "objectClassName" : "nameserver",
         "ipAddresses" : {
            "v4" : [
               "77.67.63.105"
            ],
            "v6" : [
               "2001:668:1f:11:0:0:0:105"
            ]
         }
      },
      {
         "ldhName" : "N.DE.NET",
         "ipAddresses" : {
            "v6" : [
               "2001:67c:1011:1:0:0:0:53"
            ],
            "v4" : [
               "194.146.107.6"
            ]
         },
         "objectClassName" : "nameserver"
      },
      {
         "ldhName" : "S.DE.NET",
         "objectClassName" : "nameserver",
         "ipAddresses" : {
            "v6" : [
               "2003:8:14:0:0:0:0:53"
            ],
            "v4" : [
               "195.243.137.26"
            ]
         }
      },
      {
         "objectClassName" : "nameserver",
         "ipAddresses" : {
            "v6" : [
               "2a02:568:fe02:0:0:0:0:de"
            ],
            "v4" : [
               "194.246.96.1"
            ]
         },
         "ldhName" : "Z.NIC.DE"
      }
   ],
   "links" : [
      {
         "rel" : "related",
         "href" : "https://www.iana.org/domains/root/db/de.html",
         "title" : "Entry for this TLD in the Root Zone Database"
      },
      {
         "title" : "About RDAP",
         "href" : "https://about.rdap.org",
         "rel" : "related"
      },
      {
         "title" : "URL for registration services",
         "href" : "http://www.denic.de/",
         "rel" : "related"
      }
   ],
   "objectClassName" : "domain",
   "handle" : "de",
   "secureDNS" : {
      "delegationSigned" : true,
      "dsData" : [
         {
            "digest" : "f341357809a5954311ccb82ade114c6c1d724a75c0395137aa3978035425e78d",
            "algorithm" : "8",
            "digestType" : "2",
            "keyTag" : "26755"
         }
      ]
   },
   "entities" : [
      {
         "objectClassName" : "entity",
         "handle" : "de-technical",
         "roles" : [
            "technical"
         ],
         "vcardArray" : [
            "vcard",
            [
               [
                  "version",
                  {},
                  "text",
                  "4.0"
               ],
               [
                  "fn",
                  {},
                  "text",
                  "Business Services"
               ],
               [
                  "org",
                  {},
                  "text",
                  "DENIC eG"
               ],
               [
                  "adr",
                  {
                     "label" : "Theodor-Stern-Kai 1\nFrankfurt am Main 60596\nGermany"
                  },
                  "text",
                  [
                     "",
                     "",
                     "",
                     "",
                     "",
                     "",
                     ""
                  ]
               ],
               [
                  "tel",
                  {},
                  "text",
                  "+49 69 27235 272"
               ],
               [
                  "tel",
                  {
                     "type" : "fax"
                  },
                  "text",
                  "+49 69 27235 234"
               ],
               [
                  "email",
                  {},
                  "text",
                  "dbs@denic.de"
               ]
            ]
         ]
      },
      {
         "objectClassName" : "entity",
         "handle" : "de-administrative",
         "roles" : [
            "administrative"
         ],
         "vcardArray" : [
            "vcard",
            [
               [
                  "version",
                  {},
                  "text",
                  "4.0"
               ],
               [
                  "fn",
                  {},
                  "text",
                  "Vorstand DENIC eG"
               ],
               [
                  "org",
                  {},
                  "text",
                  "DENIC eG"
               ],
               [
                  "adr",
                  {
                     "label" : "Theodor-Stern-Kai 1\nFrankfurt am Main 60596\nGermany"
                  },
                  "text",
                  [
                     "",
                     "",
                     "",
                     "",
                     "",
                     "",
                     ""
                  ]
               ],
               [
                  "tel",
                  {},
                  "text",
                  "+49 69 27235 0"
               ],
               [
                  "tel",
                  {
                     "type" : "fax"
                  },
                  "text",
                  "+49 69 27235 235"
               ],
               [
                  "email",
                  {},
                  "text",
                  "ianacontact@denic.de"
               ]
            ]
         ]
      },
      {
         "objectClassName" : "entity",
         "handle" : "de-registrant",
         "vcardArray" : [
            "vcard",
            [
               [
                  "version",
                  {},
                  "text",
                  "4.0"
               ],
               [
                  "org",
                  {},
                  "text",
                  "DENIC eG"
               ],
               [
                  "adr",
                  {
                     "label" : "Theodor-Stern-Kai 1\nFrankfurt am Main 60596\nGermany"
                  },
                  "text",
                  [
                     "",
                     "",
                     "",
                     "",
                     "",
                     "",
                     ""
                  ]
               ]
            ]
         ],
         "roles" : [
            "registrant"
         ]
      }
   ],
   "ldhName" : "de",
   "events" : [
      {
         "eventAction" : "registration",
         "eventDate" : "1986-11-05"
      },
      {
         "eventDate" : "2023-04-04",
         "eventAction" : "last changed"
      },
      {
         "eventAction" : "last update of RDAP database",
         "eventDate" : "2023-07-26T13:16:48"
      }
   ],
   "port43" : "whois.iana.org"
}
