{
   "nameservers" : [
      {
         "objectClassName" : "nameserver",
         "ipAddresses" : {
            "v6" : [
               "2a01:8840:1e:0:0:0:0:31"
            ],
            "v4" : [
               "65.22.28.31"
            ]
         },
         "ldhName" : "V0N0.NIC.FLIGHTS"
      },
      {
         "ipAddresses" : {
            "v4" : [
               "65.22.29.31"
            ],
            "v6" : [
               "2a01:8840:1f:0:0:0:0:31"
            ]
         },
         "objectClassName" : "nameserver",
         "ldhName" : "V0N1.NIC.FLIGHTS"
      },
      {
         "ldhName" : "V0N2.NIC.FLIGHTS",
         "ipAddresses" : {
            "v4" : [
               "65.22.30.31"
            ],
            "v6" : [
               "2a01:8840:20:0:0:0:0:31"
            ]
         },
         "objectClassName" : "nameserver"
      },
      {
         "ldhName" : "V0N3.NIC.FLIGHTS",
         "objectClassName" : "nameserver",
         "ipAddresses" : {
            "v6" : [
               "2a01:8840:f8:0:0:0:0:31"
            ],
            "v4" : [
               "161.232.14.31"
            ]
         }
      },
      {
         "ipAddresses" : {
            "v6" : [
               "2a01:8840:21:0:0:0:0:31"
            ],
            "v4" : [
               "65.22.31.31"
            ]
         },
         "objectClassName" : "nameserver",
         "ldhName" : "V2N0.NIC.FLIGHTS"
      },
      {
         "objectClassName" : "nameserver",
         "ipAddresses" : {
            "v6" : [
               "2a01:8840:f9:0:0:0:0:31"
            ],
            "v4" : [
               "161.232.15.31"
            ]
         },
         "ldhName" : "V2N1.NIC.FLIGHTS"
      }
   ],
   "links" : [
      {
         "href" : "https://www.iana.org/domains/root/db/flights.html",
         "rel" : "related",
         "title" : "Entry for this TLD in the Root Zone Database"
      },
      {
         "href" : "https://about.rdap.org",
         "rel" : "related",
         "title" : "About RDAP"
      },
      {
         "title" : "URL for registration services",
         "rel" : "related",
         "href" : "http://www.donuts.domains/"
      }
   ],
   "notices" : [
      {
         "title" : "About This Service",
         "description" : [
            "Please note that this RDAP service is NOT provided by the IANA.",
            "",
            "For more information, please see https://about.rdap.org"
         ]
      },
      {
         "description" : [
            "IANA WHOIS server",
            "for more information on IANA, visit http://www.iana.org",
            "This query returned 1 object"
         ],
         "title" : "Comments"
      }
   ],
   "remarks" : [
      {
         "description" : [
            "The port-43 whois service for this TLD is WHOIS.NIC.FLIGHTS."
         ],
         "title" : "Whois Service"
      },
      {
         "description" : [
            "Registration information: http://www.donuts.domains/"
         ],
         "title" : "Remark"
      },
      {
         "title" : "Source",
         "description" : [
            "IANA"
         ]
      }
   ],
   "status" : [
      "active"
   ],
   "rdapConformance" : [
      "rdap_level_0"
   ],
   "port43" : "whois.iana.org",
   "events" : [
      {
         "eventDate" : "2014-01-30",
         "eventAction" : "registration"
      },
      {
         "eventDate" : "2021-11-10",
         "eventAction" : "last changed"
      },
      {
         "eventAction" : "last update of RDAP database",
         "eventDate" : "2023-07-26T13:16:49"
      }
   ],
   "entities" : [
      {
         "handle" : "flights-administrative",
         "objectClassName" : "entity",
         "roles" : [
            "administrative"
         ],
         "vcardArray" : [
            "vcard",
            [
               [
                  "version",
                  {},
                  "text",
                  "4.0"
               ],
               [
                  "fn",
                  {},
                  "text",
                  "Vice President, Engineering"
               ],
               [
                  "org",
                  {},
                  "text",
                  "Donuts Inc."
               ],
               [
                  "adr",
                  {
                     "label" : "10500 NE 8th Street, Suite 750\nBellevue WA 98004\nUnited States of America (the)"
                  },
                  "text",
                  [
                     "",
                     "",
                     "",
                     "",
                     "",
                     "",
                     ""
                  ]
               ],
               [
                  "tel",
                  {},
                  "text",
                  "+1.425.298.2200"
               ],
               [
                  "tel",
                  {
                     "type" : "fax"
                  },
                  "text",
                  "+1.425.671.0020"
               ],
               [
                  "email",
                  {},
                  "text",
                  "tldadmin@donuts.email"
               ]
            ]
         ]
      },
      {
         "handle" : "flights-technical",
         "objectClassName" : "entity",
         "vcardArray" : [
            "vcard",
            [
               [
                  "version",
                  {},
                  "text",
                  "4.0"
               ],
               [
                  "fn",
                  {},
                  "text",
                  "Senior Director, DNS Infrastructure Group"
               ],
               [
                  "org",
                  {},
                  "text",
                  "Donuts Inc."
               ],
               [
                  "adr",
                  {
                     "label" : "10500 NE 8th Street, Suite 750\nBellevue WA 98004\nUnited States of America (the)"
                  },
                  "text",
                  [
                     "",
                     "",
                     "",
                     "",
                     "",
                     "",
                     ""
                  ]
               ],
               [
                  "tel",
                  {},
                  "text",
                  "+1.425.298.2200"
               ],
               [
                  "tel",
                  {
                     "type" : "fax"
                  },
                  "text",
                  "+1.425.671.0020"
               ],
               [
                  "email",
                  {},
                  "text",
                  "tldtech@donuts.email"
               ]
            ]
         ],
         "roles" : [
            "technical"
         ]
      },
      {
         "roles" : [
            "registrant"
         ],
         "vcardArray" : [
            "vcard",
            [
               [
                  "version",
                  {},
                  "text",
                  "4.0"
               ],
               [
                  "org",
                  {},
                  "text",
                  "Binky Moon, LLC"
               ],
               [
                  "adr",
                  {
                     "label" : "c/o Donuts Inc.\n10500 NE 8th Street, Suite 750\nBellevue WA 98004\nUnited States of America (the)"
                  },
                  "text",
                  [
                     "",
                     "",
                     "",
                     "",
                     "",
                     "",
                     ""
                  ]
               ]
            ]
         ],
         "handle" : "flights-registrant",
         "objectClassName" : "entity"
      }
   ],
   "ldhName" : "flights",
   "secureDNS" : {
      "delegationSigned" : true,
      "dsData" : [
         {
            "digest" : "e78701c441507ded68434984e0842f491bb2bcef7f0f06c9b4c964aaaad7222f",
            "algorithm" : "8",
            "digestType" : "2",
            "keyTag" : "2104"
         }
      ]
   },
   "objectClassName" : "domain",
   "handle" : "flights"
}
