{
   "entities" : [
      {
         "handle" : "gov-administrative",
         "objectClassName" : "entity",
         "roles" : [
            "administrative"
         ],
         "vcardArray" : [
            "vcard",
            [
               [
                  "version",
                  {},
                  "text",
                  "4.0"
               ],
               [
                  "fn",
                  {},
                  "text",
                  "Program Manager"
               ],
               [
                  "org",
                  {},
                  "text",
                  "Cybersecurity and Infrastructure Security Agency"
               ],
               [
                  "adr",
                  {
                     "label" : "4200 Wilson Blvd.\nArlington VA 22201\nUnited States of America (the)"
                  },
                  "text",
                  [
                     "",
                     "",
                     "",
                     "",
                     "",
                     "",
                     ""
                  ]
               ],
               [
                  "tel",
                  {},
                  "text",
                  "+1 888 282 0870"
               ],
               [
                  "email",
                  {},
                  "text",
                  "dotgov@cisa.dhs.gov"
               ]
            ]
         ]
      },
      {
         "handle" : "gov-registrant",
         "objectClassName" : "entity",
         "roles" : [
            "registrant"
         ],
         "vcardArray" : [
            "vcard",
            [
               [
                  "version",
                  {},
                  "text",
                  "4.0"
               ],
               [
                  "org",
                  {},
                  "text",
                  "Cybersecurity and Infrastructure Security Agency"
               ],
               [
                  "adr",
                  {
                     "label" : "CSD/CB – Attn: Cameron Dixon\nCISA – NGR STOP 0645\n1110 N. Glebe Rd.\nArlington VA 20598-0645\nUnited States of America (the)"
                  },
                  "text",
                  [
                     "",
                     "",
                     "",
                     "",
                     "",
                     "",
                     ""
                  ]
               ]
            ]
         ]
      },
      {
         "handle" : "gov-technical",
         "objectClassName" : "entity",
         "roles" : [
            "technical"
         ],
         "vcardArray" : [
            "vcard",
            [
               [
                  "version",
                  {},
                  "text",
                  "4.0"
               ],
               [
                  "fn",
                  {},
                  "text",
                  "Registry Customer Service"
               ],
               [
                  "org",
                  {},
                  "text",
                  "Verisign, Inc."
               ],
               [
                  "adr",
                  {
                     "label" : "12061 Bluemont Way\nReston VA 20190\nUnited States of America (the)"
                  },
                  "text",
                  [
                     "",
                     "",
                     "",
                     "",
                     "",
                     "",
                     ""
                  ]
               ],
               [
                  "tel",
                  {},
                  "text",
                  "+1 877 734 4688"
               ],
               [
                  "tel",
                  {
                     "type" : "fax"
                  },
                  "text",
                  "+1 540 301 0160"
               ],
               [
                  "email",
                  {},
                  "text",
                  "registrar@dotgov.gov"
               ]
            ]
         ]
      }
   ],
   "events" : [
      {
         "eventAction" : "registration",
         "eventDate" : "1985-01-01"
      },
      {
         "eventAction" : "last changed",
         "eventDate" : "2023-08-11"
      },
      {
         "eventAction" : "last update of RDAP database",
         "eventDate" : "2023-09-01T04:36:26"
      }
   ],
   "handle" : "gov",
   "ldhName" : "gov",
   "links" : [
      {
         "href" : "https://www.iana.org/domains/root/db/gov.html",
         "rel" : "related",
         "title" : "Entry for this TLD in the Root Zone Database"
      },
      {
         "href" : "https://about.rdap.org",
         "rel" : "related",
         "title" : "About RDAP"
      },
      {
         "href" : "http://www.dotgov.gov",
         "rel" : "related",
         "title" : "URL for registration services"
      }
   ],
   "nameservers" : [
      {
         "ipAddresses" : {
            "v4" : [
               "69.36.157.30"
            ],
            "v6" : [
               "2001:500:4431:0:0:0:2:30"
            ]
         },
         "ldhName" : "A.GOV-SERVERS.NET",
         "objectClassName" : "nameserver"
      },
      {
         "ipAddresses" : {
            "v4" : [
               "209.112.123.30"
            ],
            "v6" : [
               "2620:74:27:0:0:0:2:30"
            ]
         },
         "ldhName" : "B.GOV-SERVERS.NET",
         "objectClassName" : "nameserver"
      },
      {
         "ipAddresses" : {
            "v4" : [
               "69.36.153.30"
            ],
            "v6" : [
               "2620:74:28:0:0:0:2:30"
            ]
         },
         "ldhName" : "C.GOV-SERVERS.NET",
         "objectClassName" : "nameserver"
      },
      {
         "ipAddresses" : {
            "v4" : [
               "81.19.194.30"
            ],
            "v6" : [
               "2620:74:29:0:0:0:2:30"
            ]
         },
         "ldhName" : "D.GOV-SERVERS.NET",
         "objectClassName" : "nameserver"
      }
   ],
   "notices" : [
      {
         "description" : [
            "Please note that this RDAP service is NOT provided by the IANA.",
            "",
            "For more information, please see https://about.rdap.org"
         ],
         "title" : "About This Service"
      },
      {
         "description" : [
            "IANA WHOIS server",
            "for more information on IANA, visit http://www.iana.org",
            "This query returned 1 object"
         ],
         "title" : "Comments"
      }
   ],
   "objectClassName" : "domain",
   "port43" : "whois.iana.org",
   "rdapConformance" : [
      "rdap_level_0"
   ],
   "remarks" : [
      {
         "description" : [
            "The port-43 whois service for this TLD is WHOIS.DOTGOV.GOV."
         ],
         "title" : "Whois Service"
      },
      {
         "description" : [
            "Registration information: http://www.dotgov.gov"
         ],
         "title" : "Remark"
      },
      {
         "description" : [
            "IANA"
         ],
         "title" : "Source"
      }
   ],
   "secureDNS" : {
      "delegationSigned" : true,
      "dsData" : [
         {
            "algorithm" : "8",
            "digest" : "6bc949e638442ead0bdaf0935763c8d003760384ff15ebbd5ce86bb5559561f0",
            "digestType" : "2",
            "keyTag" : "7698"
         }
      ]
   },
   "status" : [
      "active"
   ]
}
