{
   "rdapConformance" : [
      "rdap_level_0"
   ],
   "remarks" : [
      {
         "description" : [
            "The port-43 whois service for this TLD is WHOIS.NIC.KOSHER."
         ],
         "title" : "Whois Service"
      },
      {
         "title" : "Remark",
         "description" : [
            "Registration information: http://www.ok.org/"
         ]
      },
      {
         "title" : "Source",
         "description" : [
            "IANA"
         ]
      }
   ],
   "handle" : "kosher",
   "status" : [
      "active"
   ],
   "objectClassName" : "domain",
   "nameservers" : [
      {
         "objectClassName" : "nameserver",
         "ipAddresses" : {
            "v6" : [
               "2a01:8840:d6:0:0:0:0:1"
            ],
            "v4" : [
               "65.22.220.1"
            ]
         },
         "ldhName" : "A0.NIC.KOSHER"
      },
      {
         "ldhName" : "A2.NIC.KOSHER",
         "ipAddresses" : {
            "v4" : [
               "65.22.223.1"
            ],
            "v6" : [
               "2a01:8840:d9:0:0:0:0:1"
            ]
         },
         "objectClassName" : "nameserver"
      },
      {
         "ipAddresses" : {
            "v6" : [
               "2a01:8840:d7:0:0:0:0:1"
            ],
            "v4" : [
               "65.22.221.1"
            ]
         },
         "ldhName" : "B0.NIC.KOSHER",
         "objectClassName" : "nameserver"
      },
      {
         "objectClassName" : "nameserver",
         "ipAddresses" : {
            "v4" : [
               "65.22.222.1"
            ],
            "v6" : [
               "2a01:8840:d8:0:0:0:0:1"
            ]
         },
         "ldhName" : "C0.NIC.KOSHER"
      }
   ],
   "ldhName" : "kosher",
   "secureDNS" : {
      "delegationSigned" : true,
      "dsData" : [
         {
            "digest" : "c4a550145923c0f5ef17f8d247e1e1b1e11de20b1caf26605db23d4e6a5010a4",
            "keyTag" : "24490",
            "algorithm" : "8",
            "digestType" : "2"
         }
      ]
   },
   "links" : [
      {
         "title" : "Entry for this TLD in the Root Zone Database",
         "href" : "https://www.iana.org/domains/root/db/kosher.html",
         "rel" : "related"
      },
      {
         "href" : "https://about.rdap.org",
         "title" : "About RDAP",
         "rel" : "related"
      },
      {
         "title" : "URL for registration services",
         "href" : "http://www.ok.org/",
         "rel" : "related"
      }
   ],
   "events" : [
      {
         "eventDate" : "2016-06-03",
         "eventAction" : "registration"
      },
      {
         "eventAction" : "last changed",
         "eventDate" : "2020-12-08"
      },
      {
         "eventDate" : "2023-07-26T12:30:36",
         "eventAction" : "last update of RDAP database"
      }
   ],
   "notices" : [
      {
         "description" : [
            "Please note that this RDAP service is NOT provided by the IANA.",
            "",
            "For more information, please see https://about.rdap.org"
         ],
         "title" : "About This Service"
      },
      {
         "title" : "Comments",
         "description" : [
            "IANA WHOIS server",
            "for more information on IANA, visit http://www.iana.org",
            "This query returned 1 object"
         ]
      }
   ],
   "entities" : [
      {
         "vcardArray" : [
            "vcard",
            [
               [
                  "version",
                  {},
                  "text",
                  "4.0"
               ],
               [
                  "fn",
                  {},
                  "text",
                  "Manager"
               ],
               [
                  "org",
                  {},
                  "text",
                  "Kosher Marketing Assets LLC"
               ],
               [
                  "adr",
                  {
                     "label" : "391 Troy Avenue\nBrooklyn NY 11213\nUnited States of America (the)"
                  },
                  "text",
                  [
                     "",
                     "",
                     "",
                     "",
                     "",
                     "",
                     ""
                  ]
               ],
               [
                  "tel",
                  {},
                  "text",
                  "+1 718.907.9527"
               ],
               [
                  "tel",
                  {
                     "type" : "fax"
                  },
                  "text",
                  "+1 718.756.7503"
               ],
               [
                  "email",
                  {},
                  "text",
                  "chayac@ok.org"
               ]
            ]
         ],
         "handle" : "kosher-administrative",
         "roles" : [
            "administrative"
         ],
         "objectClassName" : "entity"
      },
      {
         "roles" : [
            "registrant"
         ],
         "vcardArray" : [
            "vcard",
            [
               [
                  "version",
                  {},
                  "text",
                  "4.0"
               ],
               [
                  "org",
                  {},
                  "text",
                  "Kosher Marketing Assets LLC"
               ],
               [
                  "adr",
                  {
                     "label" : "391 Troy Avenue\nBrooklyn NY 11213\nUnited States of America (the)"
                  },
                  "text",
                  [
                     "",
                     "",
                     "",
                     "",
                     "",
                     "",
                     ""
                  ]
               ]
            ]
         ],
         "handle" : "kosher-registrant",
         "objectClassName" : "entity"
      },
      {
         "objectClassName" : "entity",
         "vcardArray" : [
            "vcard",
            [
               [
                  "version",
                  {},
                  "text",
                  "4.0"
               ],
               [
                  "fn",
                  {},
                  "text",
                  "Senior Director, DNS Infrastructure Group"
               ],
               [
                  "org",
                  {},
                  "text",
                  "Afilias"
               ],
               [
                  "adr",
                  {
                     "label" : "300 Welsh Road\nBuilding 3, Suite 105\nHorsham PA 19044\nUnited States of America (the)"
                  },
                  "text",
                  [
                     "",
                     "",
                     "",
                     "",
                     "",
                     "",
                     ""
                  ]
               ],
               [
                  "tel",
                  {},
                  "text",
                  "+1 215.706.5700"
               ],
               [
                  "tel",
                  {
                     "type" : "fax"
                  },
                  "text",
                  "+1 215.706.5701"
               ],
               [
                  "email",
                  {},
                  "text",
                  "tld-tech-poc@afilias.info"
               ]
            ]
         ],
         "handle" : "kosher-technical",
         "roles" : [
            "technical"
         ]
      }
   ],
   "port43" : "whois.iana.org"
}
